[
    {
        "name": "pcalg",
        "script_filename": "pcalg.r",
        "backend": "R",
        "description": "Standard pcalg R-implementation",
        "valid_parameters": [
            {
                "name": "alpha",
                "type": "float",
                "required": "true",
                "min": "0",
                "max": "1"
            },
            {
                "name": "independence_test",
                "type": "str",
                "required": "true",
                "values": ["gaussCI", "disCI", "binCI"]
            },
            {
                "name": "cores",
                "type": "int",
                "min": "1"
            },
            {
                "name": "verbose",
                "type": "int",
                "min": "0",
                "max": "1",
                "default": "0"
            },
            {
                "name": "subset_size",
                "type": "int",
                "min": "0"
            }
        ]
    },
    {
        "name": "parallelpc",
        "script_filename": "parallelpc.r",
        "backend": "R",
        "description": "ParallelPC R-implementation",
        "valid_parameters": [
            {
                "name": "alpha",
                "type": "float",
                "required": "true",
                "min": "0",
                "max": "1"
            },
            {
                "name": "independence_test",
                "type": "str",
                "required": "true",
                "values": ["gaussCI", "disCI", "binCI"]
            },
            {
                "name": "cores",
                "type": "int",
                "min": "2"
            },
            {
                "name": "verbose",
                "type": "int",
                "min": "0",
                "max": "1",
                "default": "0"
            },
            {
                "name": "subset_size",
                "type": "int",
                "min": "0"
            }
        ]
    }
]